database_simple.py
database_simple-0.5.10.14.dist-info/licenses/LICENSE
database_simple-0.5.10.14.dist-info/WHEEL
database_simple-0.5.10.14.dist-info/METADATA
database_simple-0.5.10.14.dist-info/RECORD
