Metadata-Version: 2.4
Name: database_simple
Version: 0.5.10.14
Summary: Made by HQO (https://github.com/MAJHQO) and idea extended from library: database_creatorplus (https://pypi.org/project/database-creatorplus/)
Author-email: MAJHQO <thehqo1337@gmail.com>
License-Expression: MIT
License-File: LICENSE
